slackreact/__init__.py
slackreact/_bot.py
slackreact/_rules.py
slackreact-0.2.0.dist-info/LICENSE.md
slackreact-0.2.0.dist-info/METADATA
slackreact-0.2.0.dist-info/WHEEL
slackreact-0.2.0.dist-info/top_level.txt
slackreact-0.2.0.dist-info/RECORD
