Metadata-Version: 2.1
Name: slackreact
Version: 0.2.0
Summary: A framework to react and respond to messages on Slack.
Home-page: https://github.com/hauntsaninja/slackreact
Author: hauntsaninja
Author-email: hauntsaninja@gmail.com
Keywords: slack bot slackbot regex
Classifier: Programming Language :: Python :: 3.6
Classifier: License :: OSI Approved :: MIT License
Classifier: Operating System :: OS Independent
Classifier: Intended Audience :: Developers
Requires-Python: >=3.6
License-File: LICENSE.md
Requires-Dist: aiohttp
Requires-Dist: websockets
